[
 {
  "id":"gravity",
  "name":"gravity",
  "parent":"gravity",
  "inspector":{
   "params":[
    "ModelVersion",
    "LastModifiedDate",
    "LibraryLinkDisplay",
    "ModelBrowserVisibility",
    "Dirty",
    "Description"
   ],
   "values":[
    "1.27",
    "Fri Dec 04 15:41:14 2015",
    "disabled",
    "off",
    "off",
    ""
   ],
   "tabs":[
   ],
   "tabs_idx":[
   ]
  },
  "viewer":{
   "jshandler":"webview/handlers/ElementHandler"
  },
  "obj_viewer":[
  ]
 },
 {
  "id":"gravity:40",
  "name":"A simple 2D gravity simulation. It is of interest to examine the performance of the different solvers. Since this simulation has the characteristic of being a stiff model, the difference between using ode45 and ode23s is very apparent (use XY Graph) @Author: Moritz Ulmer @Year: 2015",
  "parent":"gravity",
  "inspector":{
   "params":[
    "Text",
    "DropShadow",
    "Interpreter",
    "FontName",
    "FontWeight",
    "FontSize",
    "FontAngle",
    "ForegroundColor",
    "BackgroundColor",
    "HorizontalAlignment",
    "UseDisplayTextAsClickCallback",
    "ClickFcn"
   ],
   "values":[
    "A simple 2D gravity simulation. It is of interest to examine the\nperformance of the different solvers. Since this simulation has\nthe characteristic of being a stiff model, the difference between\nusing ode45 and ode23s is very apparent (use XY Graph)\n@Author: Moritz Ulmer\n@Year: 2015",
    "off",
    "off",
    "auto",
    "auto",
    -1,
    "auto",
    "black",
    "white",
    "left",
    "off",
    ""
   ],
   "tabs":[
   ],
   "tabs_idx":[
   ]
  },
  "viewer":{
   "jshandler":"webview/handlers/ElementHandler"
  },
  "obj_viewer":[
  ]
 },
 {
  "id":"gravity:2",
  "name":"x Position",
  "parent":"gravity",
  "inspector":{
   "params":[
    "ExternalReset",
    "InitialConditionSource",
    "InitialCondition",
    "LimitOutput",
    "ShowSaturationPort",
    "ShowStatePort",
    "AbsoluteTolerance",
    "IgnoreLimit",
    "ZeroCross",
    "ContinuousStateAttributes",
    "LowerSaturationLimit",
    "UpperSaturationLimit"
   ],
   "values":[
    "none",
    "internal",
    "6371000+7000000",
    "off",
    "off",
    "off",
    "auto",
    "off",
    "on",
    "''",
    "-inf",
    "inf"
   ],
   "tabs":[
    "Parameter Attributes",
    "-Other"
   ],
   "tabs_idx":[
    0,
    10
   ]
  },
  "viewer":{
   "jshandler":"webview/handlers/ElementHandler"
  },
  "obj_viewer":[
  ]
 },
 {
  "id":"gravity:3",
  "name":"Earth Mass",
  "parent":"gravity",
  "inspector":{
   "params":[
    "Value",
    "VectorParams1D",
    "SampleTime",
    "OutMin",
    "OutMax",
    "OutDataTypeStr",
    "LockScale",
    "FramePeriod"
   ],
   "values":[
    "5.972*10^24",
    "on",
    "inf",
    "[]",
    "[]",
    "Inherit: Inherit from 'Constant value'",
    "off",
    "inf"
   ],
   "tabs":[
    "Main",
    "Signal Attributes",
    "-Other"
   ],
   "tabs_idx":[
    0,
    3,
    7
   ]
  },
  "viewer":{
   "jshandler":"webview/handlers/ElementHandler"
  },
  "obj_viewer":[
  ]
 },
 {
  "id":"gravity:4",
  "name":"Vehicle Mass",
  "parent":"gravity",
  "inspector":{
   "params":[
    "Value",
    "VectorParams1D",
    "SampleTime",
    "OutMin",
    "OutMax",
    "OutDataTypeStr",
    "LockScale",
    "FramePeriod"
   ],
   "values":[
    "1000",
    "on",
    "inf",
    "[]",
    "[]",
    "Inherit: Inherit from 'Constant value'",
    "off",
    "inf"
   ],
   "tabs":[
    "Main",
    "Signal Attributes",
    "-Other"
   ],
   "tabs_idx":[
    0,
    3,
    7
   ]
  },
  "viewer":{
   "jshandler":"webview/handlers/ElementHandler"
  },
  "obj_viewer":[
  ]
 },
 {
  "id":"gravity:7",
  "name":"Gravity constant",
  "parent":"gravity",
  "inspector":{
   "params":[
    "Value",
    "VectorParams1D",
    "SampleTime",
    "OutMin",
    "OutMax",
    "OutDataTypeStr",
    "LockScale",
    "FramePeriod"
   ],
   "values":[
    "6.67*10^-11",
    "on",
    "inf",
    "[]",
    "[]",
    "Inherit: Inherit from 'Constant value'",
    "off",
    "inf"
   ],
   "tabs":[
    "Main",
    "Signal Attributes",
    "-Other"
   ],
   "tabs_idx":[
    0,
    3,
    7
   ]
  },
  "viewer":{
   "jshandler":"webview/handlers/ElementHandler"
  },
  "obj_viewer":[
  ]
 },
 {
  "id":"gravity:10",
  "name":"x Accel.",
  "parent":"gravity",
  "inspector":{
   "params":[
    "Inputs",
    "Multiplication",
    "InputSameDT",
    "OutMin",
    "OutMax",
    "OutDataTypeStr",
    "LockScale",
    "RndMeth",
    "SaturateOnIntegerOverflow",
    "CollapseDim",
    "CollapseMode",
    "SampleTime"
   ],
   "values":[
    "*/",
    "Element-wise(.*)",
    "off",
    "[]",
    "[]",
    "Inherit: Inherit via internal rule",
    "off",
    "Floor",
    "off",
    "1",
    "All dimensions",
    "-1"
   ],
   "tabs":[
    "Main",
    "Signal Attributes",
    "-Other"
   ],
   "tabs_idx":[
    0,
    2,
    9
   ]
  },
  "viewer":{
   "jshandler":"webview/handlers/ElementHandler"
  },
  "obj_viewer":[
  ]
 },
 {
  "id":"gravity:11",
  "name":"x Velocity",
  "parent":"gravity",
  "inspector":{
   "params":[
    "ExternalReset",
    "InitialConditionSource",
    "InitialCondition",
    "LimitOutput",
    "ShowSaturationPort",
    "ShowStatePort",
    "AbsoluteTolerance",
    "IgnoreLimit",
    "ZeroCross",
    "ContinuousStateAttributes",
    "LowerSaturationLimit",
    "UpperSaturationLimit"
   ],
   "values":[
    "none",
    "internal",
    "0",
    "off",
    "off",
    "off",
    "auto",
    "off",
    "on",
    "''",
    "-inf",
    "inf"
   ],
   "tabs":[
    "Parameter Attributes",
    "-Other"
   ],
   "tabs_idx":[
    0,
    10
   ]
  },
  "viewer":{
   "jshandler":"webview/handlers/ElementHandler"
  },
  "obj_viewer":[
  ]
 },
 {
  "id":"gravity:12",
  "name":"X Scope",
  "parent":"gravity",
  "inspector":[
  ],
  "viewer":{
   "jshandler":"webview/handlers/ElementHandler"
  },
  "obj_viewer":[
  ]
 },
 {
  "id":"gravity:14",
  "name":"MATLAB Function",
  "parent":"gravity",
  "inspector":{
   "params":[
    "ChartUpdate",
    "supportVariableSizing",
    "SaturateOnIntegerOverflow",
    "Locked",
    "EmlDefaultFimath",
    "TreatAsFi",
    "Description",
    "Document"
   ],
   "values":[
    "INHERITED",
    1,
    1,
    0,
    "Same as MATLAB Default",
    "Fixed-point",
    "",
    ""
   ],
   "tabs":[
   ],
   "tabs_idx":[
   ]
  },
  "viewer":{
   "jshandler":"webview/handlers/ElementHandler"
  },
  "obj_viewer":{
   "href":"support/slwebview_files/gravity_14.html"
  }
 },
 {
  "id":"gravity:23",
  "name":"Mux",
  "parent":"gravity",
  "inspector":{
   "params":[
    "Inputs",
    "DisplayOption"
   ],
   "values":[
    "4",
    "bar"
   ],
   "tabs":[
   ],
   "tabs_idx":[
   ]
  },
  "viewer":{
   "jshandler":"webview/handlers/ElementHandler"
  },
  "obj_viewer":[
  ]
 },
 {
  "id":"gravity:24",
  "name":"Constant",
  "parent":"gravity",
  "inspector":{
   "params":[
    "Value",
    "VectorParams1D",
    "SampleTime",
    "OutMin",
    "OutMax",
    "OutDataTypeStr",
    "LockScale",
    "FramePeriod"
   ],
   "values":[
    "6371000",
    "on",
    "inf",
    "[]",
    "[]",
    "Inherit: Inherit from 'Constant value'",
    "off",
    "inf"
   ],
   "tabs":[
    "Main",
    "Signal Attributes",
    "-Other"
   ],
   "tabs_idx":[
    0,
    3,
    7
   ]
  },
  "viewer":{
   "jshandler":"webview/handlers/ElementHandler"
  },
  "obj_viewer":[
  ]
 },
 {
  "id":"gravity:25",
  "name":"Unary Minus1",
  "parent":"gravity",
  "inspector":{
   "params":[
    "SaturateOnIntegerOverflow",
    "SampleTime"
   ],
   "values":[
    "off",
    "-1"
   ],
   "tabs":[
    "Parameter Attributes",
    "-Other"
   ],
   "tabs_idx":[
    0,
    1
   ]
  },
  "viewer":{
   "jshandler":"webview/handlers/ElementHandler"
  },
  "obj_viewer":[
  ]
 },
 {
  "id":"gravity:29",
  "name":"y Position",
  "parent":"gravity",
  "inspector":{
   "params":[
    "ExternalReset",
    "InitialConditionSource",
    "InitialCondition",
    "LimitOutput",
    "ShowSaturationPort",
    "ShowStatePort",
    "AbsoluteTolerance",
    "IgnoreLimit",
    "ZeroCross",
    "ContinuousStateAttributes",
    "LowerSaturationLimit",
    "UpperSaturationLimit"
   ],
   "values":[
    "none",
    "internal",
    "0",
    "off",
    "off",
    "off",
    "auto",
    "off",
    "on",
    "''",
    "-inf",
    "inf"
   ],
   "tabs":[
    "Parameter Attributes",
    "-Other"
   ],
   "tabs_idx":[
    0,
    10
   ]
  },
  "viewer":{
   "jshandler":"webview/handlers/ElementHandler"
  },
  "obj_viewer":[
  ]
 },
 {
  "id":"gravity:27",
  "name":"y Accel.",
  "parent":"gravity",
  "inspector":{
   "params":[
    "Inputs",
    "Multiplication",
    "InputSameDT",
    "OutMin",
    "OutMax",
    "OutDataTypeStr",
    "LockScale",
    "RndMeth",
    "SaturateOnIntegerOverflow",
    "CollapseDim",
    "CollapseMode",
    "SampleTime"
   ],
   "values":[
    "*/",
    "Element-wise(.*)",
    "off",
    "[]",
    "[]",
    "Inherit: Inherit via internal rule",
    "off",
    "Floor",
    "off",
    "1",
    "All dimensions",
    "-1"
   ],
   "tabs":[
    "Main",
    "Signal Attributes",
    "-Other"
   ],
   "tabs_idx":[
    0,
    2,
    9
   ]
  },
  "viewer":{
   "jshandler":"webview/handlers/ElementHandler"
  },
  "obj_viewer":[
  ]
 },
 {
  "id":"gravity:28",
  "name":"y Velocity",
  "parent":"gravity",
  "inspector":{
   "params":[
    "ExternalReset",
    "InitialConditionSource",
    "InitialCondition",
    "LimitOutput",
    "ShowSaturationPort",
    "ShowStatePort",
    "AbsoluteTolerance",
    "IgnoreLimit",
    "ZeroCross",
    "ContinuousStateAttributes",
    "LowerSaturationLimit",
    "UpperSaturationLimit"
   ],
   "values":[
    "none",
    "internal",
    "5000",
    "off",
    "off",
    "off",
    "auto",
    "off",
    "on",
    "''",
    "-inf",
    "inf"
   ],
   "tabs":[
    "Parameter Attributes",
    "-Other"
   ],
   "tabs_idx":[
    0,
    10
   ]
  },
  "viewer":{
   "jshandler":"webview/handlers/ElementHandler"
  },
  "obj_viewer":[
  ]
 },
 {
  "id":"gravity:30",
  "name":"Y Scope",
  "parent":"gravity",
  "inspector":[
  ],
  "viewer":{
   "jshandler":"webview/handlers/ElementHandler"
  },
  "obj_viewer":[
  ]
 },
 {
  "id":"gravity:31",
  "name":"Mux1",
  "parent":"gravity",
  "inspector":{
   "params":[
    "Inputs",
    "DisplayOption"
   ],
   "values":[
    "4",
    "bar"
   ],
   "tabs":[
   ],
   "tabs_idx":[
   ]
  },
  "viewer":{
   "jshandler":"webview/handlers/ElementHandler"
  },
  "obj_viewer":[
  ]
 },
 {
  "id":"gravity:32",
  "name":"z = sqrt(x² + y²)",
  "parent":"gravity",
  "inspector":{
   "params":[
    "Expr",
    "SampleTime"
   ],
   "values":[
    "sqrt(u(1)^2+u(2)^2)",
    "-1"
   ],
   "tabs":[
    "Parameter Attributes",
    "-Other"
   ],
   "tabs_idx":[
    0,
    1
   ]
  },
  "viewer":{
   "jshandler":"webview/handlers/ElementHandler"
  },
  "obj_viewer":[
  ]
 },
 {
  "id":"gravity:33",
  "name":"Mux2",
  "parent":"gravity",
  "inspector":{
   "params":[
    "Inputs",
    "DisplayOption"
   ],
   "values":[
    "2",
    "bar"
   ],
   "tabs":[
   ],
   "tabs_idx":[
   ]
  },
  "viewer":{
   "jshandler":"webview/handlers/ElementHandler"
  },
  "obj_viewer":[
  ]
 },
 {
  "id":"gravity:34",
  "name":"Fy = sin(alpha) * Fz",
  "parent":"gravity",
  "inspector":{
   "params":[
    "Expr",
    "SampleTime"
   ],
   "values":[
    "sin(u(2)) * u(1)",
    "-1"
   ],
   "tabs":[
    "Parameter Attributes",
    "-Other"
   ],
   "tabs_idx":[
    0,
    1
   ]
  },
  "viewer":{
   "jshandler":"webview/handlers/ElementHandler"
  },
  "obj_viewer":[
  ]
 },
 {
  "id":"gravity:35",
  "name":"Fx = cos(alpha) * Fz",
  "parent":"gravity",
  "inspector":{
   "params":[
    "Expr",
    "SampleTime"
   ],
   "values":[
    "cos(u(2))*u(1)",
    "-1"
   ],
   "tabs":[
    "Parameter Attributes",
    "-Other"
   ],
   "tabs_idx":[
    0,
    1
   ]
  },
  "viewer":{
   "jshandler":"webview/handlers/ElementHandler"
  },
  "obj_viewer":[
  ]
 },
 {
  "id":"gravity:36",
  "name":"alpha = atan(y / x)",
  "parent":"gravity",
  "inspector":{
   "params":[
    "Expr",
    "SampleTime"
   ],
   "values":[
    "atan2(u(1), u(2))",
    "-1"
   ],
   "tabs":[
    "Parameter Attributes",
    "-Other"
   ],
   "tabs_idx":[
    0,
    1
   ]
  },
  "viewer":{
   "jshandler":"webview/handlers/ElementHandler"
  },
  "obj_viewer":[
  ]
 },
 {
  "id":"gravity:37",
  "name":"Mux3",
  "parent":"gravity",
  "inspector":{
   "params":[
    "Inputs",
    "DisplayOption"
   ],
   "values":[
    "2",
    "bar"
   ],
   "tabs":[
   ],
   "tabs_idx":[
   ]
  },
  "viewer":{
   "jshandler":"webview/handlers/ElementHandler"
  },
  "obj_viewer":[
  ]
 },
 {
  "id":"gravity:38",
  "name":"XY Graph",
  "parent":"gravity",
  "inspector":{
   "params":[
    "xmin",
    "xmax",
    "ymin",
    "ymax",
    "st"
   ],
   "values":[
    "-20000000",
    "20000000",
    "-20000000",
    "20000000",
    "-1"
   ],
   "tabs":[
   ],
   "tabs_idx":[
   ]
  },
  "viewer":{
   "jshandler":"webview/handlers/ContainerHandler",
   "trgSid":"gravity:38"
  },
  "obj_viewer":[
  ]
 },
 {
  "id":"gravity:4#out:1",
  "name":"m",
  "parent":"gravity",
  "inspector":{
   "params":[
    "SignalNameFromLabel",
    "MustResolveToSignal",
    "ShowPropagatedSignal",
    "DataLogging",
    "TestPoint",
    "SignalObjectPackage",
    "StorageClass",
    "Description",
    "documentLink"
   ],
   "values":[
    "m",
    "off",
    "off",
    "off",
    "off",
    "--- None ---",
    "Auto",
    "",
    ""
   ],
   "tabs":[
    "Logging and accessibility",
    "Code Generation",
    "Documentation"
   ],
   "tabs_idx":[
    3,
    5,
    7
   ]
  },
  "viewer":{
   "jshandler":"webview/handlers/ElementHandler"
  },
  "obj_viewer":[
  ]
 },
 {
  "id":"gravity:10#out:1",
  "name":"a",
  "parent":"gravity",
  "inspector":{
   "params":[
    "SignalNameFromLabel",
    "MustResolveToSignal",
    "ShowPropagatedSignal",
    "DataLogging",
    "TestPoint",
    "SignalObjectPackage",
    "StorageClass",
    "Description",
    "documentLink"
   ],
   "values":[
    "a",
    "off",
    "off",
    "off",
    "off",
    "--- None ---",
    "Auto",
    "",
    ""
   ],
   "tabs":[
    "Logging and accessibility",
    "Code Generation",
    "Documentation"
   ],
   "tabs_idx":[
    3,
    5,
    7
   ]
  },
  "viewer":{
   "jshandler":"webview/handlers/ElementHandler"
  },
  "obj_viewer":[
  ]
 },
 {
  "id":"gravity:11#out:1",
  "name":"v",
  "parent":"gravity",
  "inspector":{
   "params":[
    "SignalNameFromLabel",
    "MustResolveToSignal",
    "ShowPropagatedSignal",
    "DataLogging",
    "TestPoint",
    "SignalObjectPackage",
    "StorageClass",
    "Description",
    "documentLink"
   ],
   "values":[
    "v",
    "off",
    "off",
    "off",
    "off",
    "--- None ---",
    "Auto",
    "",
    ""
   ],
   "tabs":[
    "Logging and accessibility",
    "Code Generation",
    "Documentation"
   ],
   "tabs_idx":[
    3,
    5,
    7
   ]
  },
  "viewer":{
   "jshandler":"webview/handlers/ElementHandler"
  },
  "obj_viewer":[
  ]
 },
 {
  "id":"gravity:2#out:1",
  "name":"x",
  "parent":"gravity",
  "inspector":{
   "params":[
    "SignalNameFromLabel",
    "MustResolveToSignal",
    "ShowPropagatedSignal",
    "DataLogging",
    "TestPoint",
    "SignalObjectPackage",
    "StorageClass",
    "Description",
    "documentLink"
   ],
   "values":[
    "x",
    "off",
    "off",
    "off",
    "off",
    "--- None ---",
    "Auto",
    "",
    ""
   ],
   "tabs":[
    "Logging and accessibility",
    "Code Generation",
    "Documentation"
   ],
   "tabs_idx":[
    3,
    5,
    7
   ]
  },
  "viewer":{
   "jshandler":"webview/handlers/ElementHandler"
  },
  "obj_viewer":[
  ]
 },
 {
  "id":"gravity:3#out:1",
  "name":"",
  "parent":"gravity",
  "inspector":{
   "params":[
    "SignalNameFromLabel",
    "MustResolveToSignal",
    "ShowPropagatedSignal",
    "DataLogging",
    "TestPoint",
    "SignalObjectPackage",
    "StorageClass",
    "Description",
    "documentLink"
   ],
   "values":[
    "",
    "off",
    "off",
    "off",
    "off",
    "--- None ---",
    "Auto",
    "",
    ""
   ],
   "tabs":[
    "Logging and accessibility",
    "Code Generation",
    "Documentation"
   ],
   "tabs_idx":[
    3,
    5,
    7
   ]
  },
  "viewer":{
   "jshandler":"webview/handlers/ElementHandler"
  },
  "obj_viewer":[
  ]
 },
 {
  "id":"gravity:7#out:1",
  "name":"",
  "parent":"gravity",
  "inspector":{
   "params":[
    "SignalNameFromLabel",
    "MustResolveToSignal",
    "ShowPropagatedSignal",
    "DataLogging",
    "TestPoint",
    "SignalObjectPackage",
    "StorageClass",
    "Description",
    "documentLink"
   ],
   "values":[
    "",
    "off",
    "off",
    "off",
    "off",
    "--- None ---",
    "Auto",
    "",
    ""
   ],
   "tabs":[
    "Logging and accessibility",
    "Code Generation",
    "Documentation"
   ],
   "tabs_idx":[
    3,
    5,
    7
   ]
  },
  "viewer":{
   "jshandler":"webview/handlers/ElementHandler"
  },
  "obj_viewer":[
  ]
 },
 {
  "id":"gravity:24#out:1",
  "name":"",
  "parent":"gravity",
  "inspector":{
   "params":[
    "SignalNameFromLabel",
    "MustResolveToSignal",
    "ShowPropagatedSignal",
    "DataLogging",
    "TestPoint",
    "SignalObjectPackage",
    "StorageClass",
    "Description",
    "documentLink"
   ],
   "values":[
    "",
    "off",
    "off",
    "off",
    "off",
    "--- None ---",
    "Auto",
    "",
    ""
   ],
   "tabs":[
    "Logging and accessibility",
    "Code Generation",
    "Documentation"
   ],
   "tabs_idx":[
    3,
    5,
    7
   ]
  },
  "viewer":{
   "jshandler":"webview/handlers/ElementHandler"
  },
  "obj_viewer":[
  ]
 },
 {
  "id":"gravity:25#out:1",
  "name":"",
  "parent":"gravity",
  "inspector":{
   "params":[
    "SignalNameFromLabel",
    "MustResolveToSignal",
    "ShowPropagatedSignal",
    "DataLogging",
    "TestPoint",
    "SignalObjectPackage",
    "StorageClass",
    "Description",
    "documentLink"
   ],
   "values":[
    "",
    "off",
    "off",
    "off",
    "off",
    "--- None ---",
    "Auto",
    "",
    ""
   ],
   "tabs":[
    "Logging and accessibility",
    "Code Generation",
    "Documentation"
   ],
   "tabs_idx":[
    3,
    5,
    7
   ]
  },
  "viewer":{
   "jshandler":"webview/handlers/ElementHandler"
  },
  "obj_viewer":[
  ]
 },
 {
  "id":"gravity:27#out:1",
  "name":"a",
  "parent":"gravity",
  "inspector":{
   "params":[
    "SignalNameFromLabel",
    "MustResolveToSignal",
    "ShowPropagatedSignal",
    "DataLogging",
    "TestPoint",
    "SignalObjectPackage",
    "StorageClass",
    "Description",
    "documentLink"
   ],
   "values":[
    "a",
    "off",
    "off",
    "off",
    "off",
    "--- None ---",
    "Auto",
    "",
    ""
   ],
   "tabs":[
    "Logging and accessibility",
    "Code Generation",
    "Documentation"
   ],
   "tabs_idx":[
    3,
    5,
    7
   ]
  },
  "viewer":{
   "jshandler":"webview/handlers/ElementHandler"
  },
  "obj_viewer":[
  ]
 },
 {
  "id":"gravity:28#out:1",
  "name":"v",
  "parent":"gravity",
  "inspector":{
   "params":[
    "SignalNameFromLabel",
    "MustResolveToSignal",
    "ShowPropagatedSignal",
    "DataLogging",
    "TestPoint",
    "SignalObjectPackage",
    "StorageClass",
    "Description",
    "documentLink"
   ],
   "values":[
    "v",
    "off",
    "off",
    "off",
    "off",
    "--- None ---",
    "Auto",
    "",
    ""
   ],
   "tabs":[
    "Logging and accessibility",
    "Code Generation",
    "Documentation"
   ],
   "tabs_idx":[
    3,
    5,
    7
   ]
  },
  "viewer":{
   "jshandler":"webview/handlers/ElementHandler"
  },
  "obj_viewer":[
  ]
 },
 {
  "id":"gravity:29#out:1",
  "name":"y",
  "parent":"gravity",
  "inspector":{
   "params":[
    "SignalNameFromLabel",
    "MustResolveToSignal",
    "ShowPropagatedSignal",
    "DataLogging",
    "TestPoint",
    "SignalObjectPackage",
    "StorageClass",
    "Description",
    "documentLink"
   ],
   "values":[
    "y",
    "off",
    "off",
    "off",
    "off",
    "--- None ---",
    "Auto",
    "",
    ""
   ],
   "tabs":[
    "Logging and accessibility",
    "Code Generation",
    "Documentation"
   ],
   "tabs_idx":[
    3,
    5,
    7
   ]
  },
  "viewer":{
   "jshandler":"webview/handlers/ElementHandler"
  },
  "obj_viewer":[
  ]
 },
 {
  "id":"gravity:33#out:1",
  "name":"",
  "parent":"gravity",
  "inspector":{
   "params":[
    "SignalNameFromLabel",
    "MustResolveToSignal",
    "ShowPropagatedSignal",
    "DataLogging",
    "TestPoint",
    "SignalObjectPackage",
    "StorageClass",
    "Description",
    "documentLink"
   ],
   "values":[
    "",
    "off",
    "off",
    "off",
    "off",
    "--- None ---",
    "Auto",
    "",
    ""
   ],
   "tabs":[
    "Logging and accessibility",
    "Code Generation",
    "Documentation"
   ],
   "tabs_idx":[
    3,
    5,
    7
   ]
  },
  "viewer":{
   "jshandler":"webview/handlers/ElementHandler"
  },
  "obj_viewer":[
  ]
 },
 {
  "id":"gravity:32#out:1",
  "name":"z",
  "parent":"gravity",
  "inspector":{
   "params":[
    "SignalNameFromLabel",
    "MustResolveToSignal",
    "ShowPropagatedSignal",
    "DataLogging",
    "TestPoint",
    "SignalObjectPackage",
    "StorageClass",
    "Description",
    "documentLink"
   ],
   "values":[
    "z",
    "off",
    "off",
    "off",
    "off",
    "--- None ---",
    "Auto",
    "",
    ""
   ],
   "tabs":[
    "Logging and accessibility",
    "Code Generation",
    "Documentation"
   ],
   "tabs_idx":[
    3,
    5,
    7
   ]
  },
  "viewer":{
   "jshandler":"webview/handlers/ElementHandler"
  },
  "obj_viewer":[
  ]
 },
 {
  "id":"gravity:35#out:1",
  "name":"",
  "parent":"gravity",
  "inspector":{
   "params":[
    "SignalNameFromLabel",
    "MustResolveToSignal",
    "ShowPropagatedSignal",
    "DataLogging",
    "TestPoint",
    "SignalObjectPackage",
    "StorageClass",
    "Description",
    "documentLink"
   ],
   "values":[
    "",
    "off",
    "off",
    "off",
    "off",
    "--- None ---",
    "Auto",
    "",
    ""
   ],
   "tabs":[
    "Logging and accessibility",
    "Code Generation",
    "Documentation"
   ],
   "tabs_idx":[
    3,
    5,
    7
   ]
  },
  "viewer":{
   "jshandler":"webview/handlers/ElementHandler"
  },
  "obj_viewer":[
  ]
 },
 {
  "id":"gravity:34#out:1",
  "name":"",
  "parent":"gravity",
  "inspector":{
   "params":[
    "SignalNameFromLabel",
    "MustResolveToSignal",
    "ShowPropagatedSignal",
    "DataLogging",
    "TestPoint",
    "SignalObjectPackage",
    "StorageClass",
    "Description",
    "documentLink"
   ],
   "values":[
    "",
    "off",
    "off",
    "off",
    "off",
    "--- None ---",
    "Auto",
    "",
    ""
   ],
   "tabs":[
    "Logging and accessibility",
    "Code Generation",
    "Documentation"
   ],
   "tabs_idx":[
    3,
    5,
    7
   ]
  },
  "viewer":{
   "jshandler":"webview/handlers/ElementHandler"
  },
  "obj_viewer":[
  ]
 },
 {
  "id":"gravity:36#out:1",
  "name":"alpha",
  "parent":"gravity",
  "inspector":{
   "params":[
    "SignalNameFromLabel",
    "MustResolveToSignal",
    "ShowPropagatedSignal",
    "DataLogging",
    "TestPoint",
    "SignalObjectPackage",
    "StorageClass",
    "Description",
    "documentLink"
   ],
   "values":[
    "alpha",
    "off",
    "off",
    "off",
    "off",
    "--- None ---",
    "Auto",
    "",
    ""
   ],
   "tabs":[
    "Logging and accessibility",
    "Code Generation",
    "Documentation"
   ],
   "tabs_idx":[
    3,
    5,
    7
   ]
  },
  "viewer":{
   "jshandler":"webview/handlers/ElementHandler"
  },
  "obj_viewer":[
  ]
 },
 {
  "id":"gravity:37#out:1",
  "name":"",
  "parent":"gravity",
  "inspector":{
   "params":[
    "SignalNameFromLabel",
    "MustResolveToSignal",
    "ShowPropagatedSignal",
    "DataLogging",
    "TestPoint",
    "SignalObjectPackage",
    "StorageClass",
    "Description",
    "documentLink"
   ],
   "values":[
    "",
    "off",
    "off",
    "off",
    "off",
    "--- None ---",
    "Auto",
    "",
    ""
   ],
   "tabs":[
    "Logging and accessibility",
    "Code Generation",
    "Documentation"
   ],
   "tabs_idx":[
    3,
    5,
    7
   ]
  },
  "viewer":{
   "jshandler":"webview/handlers/ElementHandler"
  },
  "obj_viewer":[
  ]
 },
 {
  "id":"gravity:23#out:1",
  "name":"",
  "parent":"gravity",
  "inspector":{
   "params":[
    "SignalNameFromLabel",
    "MustResolveToSignal",
    "ShowPropagatedSignal",
    "DataLogging",
    "TestPoint",
    "SignalObjectPackage",
    "StorageClass",
    "Description",
    "documentLink"
   ],
   "values":[
    "",
    "off",
    "off",
    "off",
    "off",
    "--- None ---",
    "Auto",
    "",
    ""
   ],
   "tabs":[
    "Logging and accessibility",
    "Code Generation",
    "Documentation"
   ],
   "tabs_idx":[
    3,
    5,
    7
   ]
  },
  "viewer":{
   "jshandler":"webview/handlers/ElementHandler"
  },
  "obj_viewer":[
  ]
 },
 {
  "id":"gravity:31#out:1",
  "name":"",
  "parent":"gravity",
  "inspector":{
   "params":[
    "SignalNameFromLabel",
    "MustResolveToSignal",
    "ShowPropagatedSignal",
    "DataLogging",
    "TestPoint",
    "SignalObjectPackage",
    "StorageClass",
    "Description",
    "documentLink"
   ],
   "values":[
    "",
    "off",
    "off",
    "off",
    "off",
    "--- None ---",
    "Auto",
    "",
    ""
   ],
   "tabs":[
    "Logging and accessibility",
    "Code Generation",
    "Documentation"
   ],
   "tabs_idx":[
    3,
    5,
    7
   ]
  },
  "viewer":{
   "jshandler":"webview/handlers/ElementHandler"
  },
  "obj_viewer":[
  ]
 },
 {
  "id":"gravity:14#out:1",
  "name":"F",
  "parent":"gravity",
  "inspector":{
   "params":[
    "SignalNameFromLabel",
    "MustResolveToSignal",
    "ShowPropagatedSignal",
    "DataLogging",
    "TestPoint",
    "SignalObjectPackage",
    "StorageClass",
    "Description",
    "documentLink"
   ],
   "values":[
    "F",
    "off",
    "off",
    "off",
    "off",
    "--- None ---",
    "Auto",
    "",
    ""
   ],
   "tabs":[
    "Logging and accessibility",
    "Code Generation",
    "Documentation"
   ],
   "tabs_idx":[
    3,
    5,
    7
   ]
  },
  "viewer":{
   "jshandler":"webview/handlers/ElementHandler"
  },
  "obj_viewer":[
  ]
 }
]